{"type":"PR","pr":{"number":14,"head":"048d60f51b3e94ebcd65c5e3fb76ae25cd1bc029"},"user":"Jeftar Mascarenhas","status":"pending_publish","branch":"cms/2020-02-24-novos-métodos-do-objeto-string-no-js","collection":"blog","title":"4 Métodos úteis do Objeto String no JS","description":"Conheça os novos métodos de String que são úteis para trabalhar no dia a dia.","objects":{"entry":{"path":"content/posts/2020-02-24-novos-métodos-do-objeto-string-no-js.md","sha":"660ae0f8641c2e2191ccb85c45a4939a6d141a71"},"files":[]},"timeStamp":"2020-02-26T03:42:09.583Z"}